{
  "kind": "collectionType",
  "collectionName": "transactions",
  "info": {
    "singularName": "transaction",
    "pluralName": "transactions",
    "displayName": "transaction",
    "description": ""
  },
  "options": {
    "draftAndPublish": false
  },
  "pluginOptions": {},
  "attributes": {
    "description": {
      "type": "string"
    },
    "value": {
      "type": "decimal"
    },
    "bank": {
      "type": "relation",
      "relation": "oneToOne",
      "target": "api::bank.bank"
    }
  }
}
